{
    "card_definition": {
        "idx": 17,
        "name": "The Tower",
        "description": "The Tower(탑)는 갑작스러운 변화, 붕괴, 그리고 혼란을 상징한다. 이 카드는 예상치 못한 사건이나 변화를 경고하며, 그로 인해 기존의 시스템이나 신념이 무너질 수 있음을 알린다. 그러나 이 혼란 속에서도 새로운 기회가 탄생할 수 있음을 나타낸다.\n\n이 카드는 너에게 갑작스러운 변화와 그로 인한 혼란을 받아들이라고 조언한다. 이러한 변화는 어렵고 고통스러울 수 있지만, 결국에는 더 나은 미래로 나아가기 위한 중요한 과정이 될 것이다. 이 시간을 통해 새롭게 재정비하고 더 강해질 수 있는 기회로 삼아라."
    },
    "interpretations": [
        {
            "idx": 17,
            "type": 0,
            "direction": "Reverse",
            "interpretation": "과거에 너는 갑작스러운 변화에 대응하지 못했거나 그 변화를 거부했을 수 있다. 그로 인해 더 큰 혼란이 찾아왔을지도 모른다. 이 경험은 너에게 변화에 유연하게 대처하는 법을 가르쳐주었다."
        },
        {
            "idx": 17,
            "type": 1,
            "direction": "Reverse",
            "interpretation": "현재, 너는 큰 변화와 혼란을 겪고 있다. 너는 이 변화를 거부하거나 외면하려 할 수 있지만, 그것은 상황을 악화시킬 뿐이다. 이 혼란 속에서도 새로운 기회를 찾는 법을 배워야 한다."
        },
        {
            "idx": 17,
            "type": 2,
            "direction": "Reverse",
            "interpretation": "미래에는 예상치 못한 큰 변화가 다가올 것이다. 그 변화가 처음에는 혼란을 일으킬 수 있지만, 결국에는 더 나은 방향으로 나아가기 위한 과정이 될 것이다."
        },
        {
            "idx": 17,
            "type": 0,
            "direction": "Forward",
            "interpretation": "과거에 너는 큰 변화를 성공적으로 받아들였고, 그로 인해 중요한 성장을 이루었다. 너는 혼란 속에서도 새로운 기회를 발견하고, 그 기회를 통해 더 나은 결과를 얻을 수 있었다."
        },
        {
            "idx": 17,
            "type": 1,
            "direction": "Forward",
            "interpretation": "현재, 너는 변화를 잘 관리하고 있으며, 그로 인해 긍정적인 결과를 얻고 있다. 너는 혼란 속에서도 냉정함을 유지하며 새로운 기회를 찾고 있다."
        },
        {
            "idx": 17,
            "type": 2,
            "direction": "Forward",
            "interpretation": "미래에 너는 더 큰 변화를 마주하게 될 것이며, 그 변화는 너에게 새로운 기회를 열어줄 것이다. 그 변화를 통해 더 나은 미래로 나아갈 수 있을 것이다."
        }
    ]
}